AUTHORS.rst
CONTRIBUTING.rst
HISTORY.rst
LICENSE
MANIFEST.in
README.rst
setup.cfg
setup.py
docs/Makefile
docs/authors.rst
docs/conf.py
docs/contributing.rst
docs/history.rst
docs/index.rst
docs/installation.rst
docs/make.bat
docs/readme.rst
docs/usage.rst
lstree/__init__.py
lstree/__main__.py
lstree/treeconfig.py
lstree.egg-info/PKG-INFO
lstree.egg-info/SOURCES.txt
lstree.egg-info/dependency_links.txt
lstree.egg-info/entry_points.txt
lstree.egg-info/not-zip-safe
lstree.egg-info/top_level.txt
lstree/nodes/__init__.py
lstree/nodes/directory.py
lstree/nodes/file.py
lstree/nodes/node.py
lstree/nodetree/__init__.py
lstree/nodetree/builder.py
lstree/nodetree/plotter.py
lstree/nodetree/visitor.py
tests/__init__.py
tests/test_nodeTreeBuilder.py