Metadata-Version: 1.1
Name: lstree
Version: 0.1.0
Summary: lstree is for ls what pstree is for ps, and some more
Home-page: https://github.com/shreyas/lstree
Author: Shreyas Kulkarni
Author-email: shyran@gmail.com
License: MIT
Keywords: lstree
Platform: UNKNOWN
Classifier: Development Status :: 2 - Pre-Alpha
Classifier: Intended Audience :: Developers
Classifier: License :: OSI Approved :: MIT License
Classifier: Natural Language :: English
Classifier: Programming Language :: Python :: 2
Classifier: Programming Language :: Python :: 2.6
Classifier: Programming Language :: Python :: 2.7
Classifier: Programming Language :: Python :: 3
Classifier: Programming Language :: Python :: 3.3
Classifier: Programming Language :: Python :: 3.4
Classifier: Programming Language :: Python :: 3.5
